README.rst
setup.py
harry/__init__.py
harry/harry.py
harry.egg-info/PKG-INFO
harry.egg-info/SOURCES.txt
harry.egg-info/__init__.py
harry.egg-info/dependency_links.txt
harry.egg-info/entry_points.txt
harry.egg-info/requires.txt
harry.egg-info/top_level.txt
harry/harpy/LICENSE.txt
harry/harpy/__init__.py
harry/harpy/__init__.pyc
harry/harpy/harpy
harry/harpy/harpy/__init__.py
harry/harpy/harpy/__init__.pyc
harry/harpy/harpy/cache.py
harry/harpy/harpy/cache.pyc
harry/harpy/harpy/content.py
harry/harpy/harpy/content.pyc
harry/harpy/harpy/cookie.py
harry/harpy/harpy/cookie.pyc
harry/harpy/harpy/entry.py
harry/harpy/harpy/entry.pyc
harry/harpy/harpy/har.py
harry/harpy/harpy/har.pyc
harry/harpy/harpy/header.py
harry/harpy/harpy/header.pyc
harry/harpy/harpy/page.py
harry/harpy/harpy/page.pyc
harry/harpy/harpy/post_data.py
harry/harpy/harpy/query_string.py
harry/harpy/harpy/query_string.pyc
harry/harpy/harpy/request.py
harry/harpy/harpy/request.pyc
harry/harpy/harpy/response.py
harry/harpy/harpy/response.pyc
harry/harpy/harpy/timings.py
harry/harpy/harpy/timings.pyc