Metadata-Version: 1.0
Name: harry
Version: 0.0.22
Summary: harry converts HTTP Archives (.har) into JMeter test plans (.jmx).
Home-page: https://github.com/munrocape/harry
Author: Zach Munro-Cape
Author-email: zach.munrocape@gmail.com
License: apache
Keywords: jmeter,http archive,har2jmx,command line,cli
Platform: UNKNOWN
